pia_ctl_sdk-0.1.3.dist-info/METADATA
pia_ctl_sdk-0.1.3.dist-info/WHEEL
pia_ctl_sdk-0.1.3.dist-info/entry_points.txt
pia_ctl_sdk-0.1.3.dist-info/licenses/LICENSE
pypia_ctl/__init__.py
pypia_ctl/adapters.py
pypia_ctl/authcheck.py
pypia_ctl/bootstrap.py
pypia_ctl/cli.py
pypia_ctl/config.py
pypia_ctl/core.py
pypia_ctl/envtools.py
pypia_ctl/exceptions.py
pypia_ctl/plugins.py
pia_ctl_sdk-0.1.3.dist-info/RECORD
